Metadata-Version: 1.0
Name: distributions-try
Version: 1.0
Summary: Gaussian and Binomial distributions
Home-page: UNKNOWN
Author: Ali Rahman
Author-email: alirman02@gmail.com
License: UNKNOWN
Platform: UNKNOWN
